amazon_search_scraper_bc/__init__.py
amazon_search_scraper_bc/scraper.py
amazon_search_scraper_bc-1.1.2.dist-info/METADATA
amazon_search_scraper_bc-1.1.2.dist-info/WHEEL
amazon_search_scraper_bc-1.1.2.dist-info/top_level.txt
amazon_search_scraper_bc-1.1.2.dist-info/RECORD
