Metadata-Version: 2.1
Name: amazon-search-scraper-bc
Version: 1.1.2
Summary: A package that fethes data from amazon.
Home-page: https://github.com/barno1994/amazon_search_scraper_bc
Author: barno1994 (Barno Chakraborty)
Author-email: <barno.baptu@gmail.com>
License: UNKNOWN
Keywords: amazon,scraper,amazonscraper,amazon search
Platform: UNKNOWN
Classifier: Development Status :: 2 - Pre-Alpha
Classifier: Intended Audience :: Developers
Classifier: Programming Language :: Python :: 3
Classifier: Operating System :: Unix
Classifier: Operating System :: MacOS :: MacOS X
Classifier: Operating System :: Microsoft :: Windows
Requires-Dist: beautifulsoup4
Requires-Dist: bottlenose
Requires-Dist: bs4
Requires-Dist: lxml
Requires-Dist: python-dateutil
Requires-Dist: requests
Requires-Dist: selenium
Requires-Dist: six
Requires-Dist: soupsieve
Requires-Dist: urllib3
